uw_pws/VERSION
uw_pws/__init__.py
uw_pws/dao.py
uw_pws/exceptions.py
uw_pws/models.py
uw_pws/test.py
uw_pws/util.py
uw_pws/resources/pws/file/idcard/v1/card.json_prox_rfid_1223221621633408
uw_pws/resources/pws/file/idcard/v1/photo/9136CCB8F66711D5BE060004AC494FFE-100.jpg
uw_pws/resources/pws/file/idcard/v1/photo/9136CCB8F66711D5BE060004AC494FFE-large.jpg
uw_pws/resources/pws/file/idcard/v1/photo/9136CCB8F66711D5BE060004AC494FFE-medium.jpg
uw_pws/resources/pws/file/idcard/v1/photo/9136CCB8F66711D5BE060004AC494FFE-small.jpg
uw_pws/resources/pws/file/identity/v2/entity.json_is_test_entity_true_page_size_250
uw_pws/resources/pws/file/identity/v2/person.json_changed_since_date_2019_page_size_250_verbose_on
uw_pws/resources/pws/file/identity/v2/person.json_changed_since_date_2019_page_size_250_verbose_on_page_start_2
uw_pws/resources/pws/file/identity/v2/person.json_employee_id_123456789_verbose_on
uw_pws/resources/pws/file/identity/v2/person.json_employee_id_999999999_verbose_on
uw_pws/resources/pws/file/identity/v2/person.json_student_number_1234567_verbose_on
uw_pws/resources/pws/file/identity/v2/person.json_student_number_9999999_verbose_on
uw_pws/resources/pws/file/identity/v2/entity/605764A811A847E690F107D763A4B32A.json
uw_pws/resources/pws/file/identity/v2/entity/javerage.json
uw_pws/resources/pws/file/identity/v2/entity/somalt.json
uw_pws/resources/pws/file/identity/v2/person/00000000000000000000000000000001.json
uw_pws/resources/pws/file/identity/v2/person/00000000000000000000000000000003.json
uw_pws/resources/pws/file/identity/v2/person/00000000000000000000000000000004.json
uw_pws/resources/pws/file/identity/v2/person/12345678901234567890123456789012.json
uw_pws/resources/pws/file/identity/v2/person/260A0DEC95CB11D78BAA000629C31437.json
uw_pws/resources/pws/file/identity/v2/person/6DF0A9206A7D11D5A4AE0004AC494FFE.json
uw_pws/resources/pws/file/identity/v2/person/9136CCB8F66711D5BE060004AC494FFE.json
uw_restclients_pws-2.1.13.dist-info/LICENSE
uw_restclients_pws-2.1.13.dist-info/METADATA
uw_restclients_pws-2.1.13.dist-info/WHEEL
uw_restclients_pws-2.1.13.dist-info/top_level.txt
uw_restclients_pws-2.1.13.dist-info/RECORD
